MANIFEST.in
libmata.cpp
libmata.pxd
libmata.pyx
pyproject.toml
setup.py
/home/runner/work/mata/mata/3rdparty/re2/re2/compile.cc
/home/runner/work/mata/mata/3rdparty/re2/re2/parse.cc
/home/runner/work/mata/mata/3rdparty/re2/re2/perl_groups.cc
/home/runner/work/mata/mata/3rdparty/re2/re2/prog.cc
/home/runner/work/mata/mata/3rdparty/re2/re2/re2.cc
/home/runner/work/mata/mata/3rdparty/re2/re2/regexp.cc
/home/runner/work/mata/mata/3rdparty/re2/re2/simplify.cc
/home/runner/work/mata/mata/3rdparty/re2/re2/stringpiece.cc
/home/runner/work/mata/mata/3rdparty/re2/re2/tostring.cc
/home/runner/work/mata/mata/3rdparty/re2/re2/unicode_casefold.cc
/home/runner/work/mata/mata/3rdparty/re2/re2/unicode_groups.cc
/home/runner/work/mata/mata/3rdparty/re2/util/rune.cc
/home/runner/work/mata/mata/3rdparty/re2/util/strutil.cc
/home/runner/work/mata/mata/3rdparty/simlib/src/explicit_lts_sim.cc
/home/runner/work/mata/mata/src/config.cc
/home/runner/work/mata/mata/src/inter-aut.cc
/home/runner/work/mata/mata/src/parser.cc
/home/runner/work/mata/mata/src/re2parser.cc
/home/runner/work/mata/mata/src/afa/afa.cc
/home/runner/work/mata/mata/src/nfa/nfa-complement.cc
/home/runner/work/mata/mata/src/nfa/nfa-concatenation.cc
/home/runner/work/mata/mata/src/nfa/nfa-inclusion.cc
/home/runner/work/mata/mata/src/nfa/nfa-intersection.cc
/home/runner/work/mata/mata/src/nfa/nfa-segmentation.cc
/home/runner/work/mata/mata/src/nfa/nfa-universal.cc
/home/runner/work/mata/mata/src/nfa/nfa.cc
/home/runner/work/mata/mata/src/nfa/noodlify.cc
/home/runner/work/mata/mata/src/rra/rrt.cc
libmata.egg-info/PKG-INFO
libmata.egg-info/SOURCES.txt
libmata.egg-info/dependency_links.txt
libmata.egg-info/requires.txt
libmata.egg-info/top_level.txt