Metadata-Version: 2.1
Name: libmata
Version: 1.13.0
Summary: The automata library
Home-page: https://github.com/verifit/mata
Author: Lukáš Holík <holik@fit.vutbr.cz>, Ondřej Lengál <lengal@fit.vutbr.cz>, Martin Hruška <ihruskam@fit.vutbr.cz>, Tomáš Fiedor <ifiedortom@fit.vutbr.cz>, David Chocholatý <chocholaty.david@protonmail.com>, Juraj Síč <sicjuraj@fit.vutbr.cz>, Tomáš Vojnar <vojnar@fit.vutbr.cz>
Author-email: lengal@fit.vutbr.cz
License: UNKNOWN
Keywords: automata,finite automata,alternating automata
Platform: UNKNOWN
